{"kind":"Notebook","sha256":"c6fa58065753e3ae450ebf456e3d94481e5c8b9eb6493092625e3931a39cfcf9","slug":"the-one-that-works","location":"/The one that works.ipynb","dependencies":[],"frontmatter":{"github":"https://github.com/HannahKerubo/JTermProject","keywords":[],"exports":[{"format":"ipynb","filename":"The one that works.ipynb","url":"/The one that works-2aa5cfb293dbefc21fa52f47905b699b.ipynb"}]},"mdast":{"type":"root","children":[{"type":"block","children":[{"type":"code","lang":"python","executable":true,"value":"%matplotlib inline\nimport pandas as pd\nimport matplotlib.pyplot as plt","key":"crrCjxnTah"},{"type":"output","id":"cowGazXeVchXOl4kHnRK7","data":[],"key":"MMKbVnuKbn"}],"data":{"type":"notebook-code"},"key":"JwITmfIdJK"},{"type":"block","children":[{"type":"code","lang":"python","executable":true,"value":"file_path = 'CTYD Kenya.csv'\ndata = pd.read_csv(file_path)","key":"bb8Yb83aBz"},{"type":"output","id":"9hd1G99DujvAIZRklMHtV","data":[],"key":"F1XKRhRCN7"}],"data":{"type":"notebook-code"},"key":"bf9qqPu1Ho"},{"type":"block","children":[{"type":"code","lang":"python","executable":true,"value":"data[ ['region', 'year', 'grp_lcu'] ].head()","identifier":"grptable-code","enumerator":"1","html_id":"grptable-code","key":"LYZbQRF3G5"},{"type":"output","id":"ivIGsrj4gQnI9sCKBC1Qc","data":[{"output_type":"execute_result","execution_count":11,"metadata":{},"data":{"text/html":{"content":"<div>\n<style scoped>\n    .dataframe tbody tr th:only-of-type {\n        vertical-align: middle;\n    }\n\n    .dataframe tbody tr th {\n        vertical-align: top;\n    }\n\n    .dataframe thead th {\n        text-align: right;\n    }\n</style>\n<table border=\"1\" class=\"dataframe\">\n  <thead>\n    <tr style=\"text-align: right;\">\n      <th></th>\n      <th>region</th>\n      <th>year</th>\n      <th>grp_lcu</th>\n    </tr>\n  </thead>\n  <tbody>\n    <tr>\n      <th>0</th>\n      <td>Baringo</td>\n      <td>2016</td>\n      <td>7.790500e+10</td>\n    </tr>\n    <tr>\n      <th>1</th>\n      <td>Baringo</td>\n      <td>2017</td>\n      <td>9.286602e+10</td>\n    </tr>\n    <tr>\n      <th>2</th>\n      <td>Bomet</td>\n      <td>2016</td>\n      <td>1.320000e+11</td>\n    </tr>\n    <tr>\n      <th>3</th>\n      <td>Bomet</td>\n      <td>2017</td>\n      <td>1.600000e+11</td>\n    </tr>\n    <tr>\n      <th>4</th>\n      <td>Bungoma</td>\n      <td>2016</td>\n      <td>1.530000e+11</td>\n    </tr>\n  </tbody>\n</table>\n</div>","content_type":"text/html"},"text/plain":{"content":"    region  year       grp_lcu\n0  Baringo  2016  7.790500e+10\n1  Baringo  2017  9.286602e+10\n2    Bomet  2016  1.320000e+11\n3    Bomet  2017  1.600000e+11\n4  Bungoma  2016  1.530000e+11","content_type":"text/plain"}}}],"identifier":"grptable-output","html_id":"grptable-output","key":"L0b0EiuX5v"}],"data":{"type":"notebook-code"},"identifier":"grptable","label":"GRPtable","html_id":"grptable","key":"EpW6vPoS26"},{"type":"block","children":[{"type":"code","lang":"python","executable":true,"value":"pivot_data = data.pivot_table(values='grp_lcu', index='region', columns='year', aggfunc='sum')","key":"Cq7E5cd7Pa"},{"type":"output","id":"NOFslE3uAZFO12Pq-dnXd","data":[],"key":"ob3baffr6Q"}],"data":{"type":"notebook-code"},"key":"TycLzD2fUW"},{"type":"block","children":[{"type":"code","lang":"python","executable":true,"value":"pivot_data.plot(kind='bar', stacked=True, color=['blue','orange'], figsize=(15, 8))\nplt.title('Gross Regional Product (grp_lcu) per Region in Kenya for 2016 and 2017')\nplt.xlabel('Region')\nplt.ylabel('Gross Regional Product (grp_lcu)')\nplt.xticks(rotation=90)\nplt.legend(title='Year')\nplt.savefig('GRPGRAPH.png')","identifier":"grpchart-code","enumerator":"2","html_id":"grpchart-code","key":"zqSsjST81c"},{"type":"output","id":"Q7DpsqDH8NbbZ2Dm6zq8i","data":[{"output_type":"display_data","metadata":{},"data":{"image/png":{"content_type":"image/png","hash":"34351b70ab2db592acb51787d74cc3cc","path":"/34351b70ab2db592acb51787d74cc3cc.png"},"text/plain":{"content":"<Figure size 1500x800 with 1 Axes>","content_type":"text/plain"}}}],"identifier":"grpchart-output","html_id":"grpchart-output","key":"G1jMnc1ABJ"}],"data":{"type":"notebook-code"},"identifier":"grpchart","label":"GRPchart","html_id":"grpchart","key":"o5dvdwNcYm"}],"key":"FGCN8RrNY7"},"references":{"cite":{"order":[],"data":{}}}}